Blauwal3_Prototypes-0.21.2-py3.10-nspkg.pth
orangecontrib/prototypes/__init__.py
orangecontrib/prototypes/i18n_config.py
orangecontrib/prototypes/interactions.py
orangecontrib/prototypes/ranktablemodel.py
orangecontrib/prototypes/locale/prototypes.de.yml
orangecontrib/prototypes/locale/prototypes.en.yml
orangecontrib/prototypes/locale/prototypes.zh.yml
orangecontrib/prototypes/modeling/__init__.py
orangecontrib/prototypes/modeling/scoringsheet.py
orangecontrib/prototypes/modeling/fasterrisk/LICENSE
orangecontrib/prototypes/modeling/fasterrisk/NOTICE
orangecontrib/prototypes/modeling/fasterrisk/__init__.py
orangecontrib/prototypes/modeling/fasterrisk/base_model.py
orangecontrib/prototypes/modeling/fasterrisk/fasterrisk.py
orangecontrib/prototypes/modeling/fasterrisk/rounding.py
orangecontrib/prototypes/modeling/fasterrisk/sparseBeamSearch.py
orangecontrib/prototypes/modeling/fasterrisk/sparseDiversePool.py
orangecontrib/prototypes/modeling/fasterrisk/utils.py
orangecontrib/prototypes/tests/__init__.py
orangecontrib/prototypes/widgets/__init__.py
orangecontrib/prototypes/widgets/owchatgpt.py
orangecontrib/prototypes/widgets/owchatgptbase.py
orangecontrib/prototypes/widgets/owchatgptconstructor.py
orangecontrib/prototypes/widgets/owdfdisplay.py
orangecontrib/prototypes/widgets/owgrep.py
orangecontrib/prototypes/widgets/owinteractions.py
orangecontrib/prototypes/widgets/oworaclesql.py
orangecontrib/prototypes/widgets/owquickselect.py
orangecontrib/prototypes/widgets/owscoringsheet.py
orangecontrib/prototypes/widgets/owscoringsheetviewer.py
orangecontrib/prototypes/widgets/owtexttocolumns.py
orangecontrib/prototypes/widgets/icons/Category-Prototypes.svg
orangecontrib/prototypes/widgets/icons/Grep.svg
orangecontrib/prototypes/widgets/icons/OracleSQL.svg
orangecontrib/prototypes/widgets/icons/QuickSelect.svg
orangecontrib/prototypes/widgets/icons/ScoringSheet.svg
orangecontrib/prototypes/widgets/icons/ScoringSheetViewer.svg
Blauwal3_Prototypes-0.21.2.dist-info/LICENSE
Blauwal3_Prototypes-0.21.2.dist-info/METADATA
Blauwal3_Prototypes-0.21.2.dist-info/WHEEL
Blauwal3_Prototypes-0.21.2.dist-info/entry_points.txt
Blauwal3_Prototypes-0.21.2.dist-info/namespace_packages.txt
Blauwal3_Prototypes-0.21.2.dist-info/top_level.txt
Blauwal3_Prototypes-0.21.2.dist-info/RECORD
